{"run_number": "1577223580010603", "step_name": "compute_statistics", "task_id": "17", "attempt_id": 0, "name": "_foreach_stack", "content_type": "gzip+pickle-v2", "type": "metaflow.artifact", "sha": "b32799e3072d0a4d9f32dc93d495eb03c982852e", "ds_type": "local", "location": "/CodeForLyf/metaflow-tutorial/.metaflow/MovieStatsFlow/data/b3/b32799e3072d0a4d9f32dc93d495eb03c982852e", "flow_id": "MovieStatsFlow", "user_name": "viveckh", "tags": [], "system_tags": ["user:viveckh", "runtime:dev", "python_version:3.7.4", "date:2019-12-24", "metaflow_version:2.0.1"], "ts_epoch": 1577223585450}